safe_cast/__init__.py
safe_cast-0.3.4.dist-info/METADATA
safe_cast-0.3.4.dist-info/RECORD
safe_cast-0.3.4.dist-info/WHEEL
safe_cast-0.3.4.dist-info/top_level.txt
