Metadata-Version: 2.1
Name: safe-cast
Version: 0.3.4
Summary: Safe casting of Python base types
Home-page: https://github.com/TuneLab/safe-cast
Author: TUNE Inc.
Author-email: jefft@tune.com
License: MIT License
Download-URL: https://github.com/TuneLab/safe-cast/archive/v0.3.4.tar.gz
Keywords: safe casting tune
Platform: UNKNOWN
Classifier: Development Status :: 5 - Production/Stable
Classifier: Intended Audience :: Developers
Classifier: Operating System :: OS Independent
Classifier: Natural Language :: English
Classifier: License :: OSI Approved :: MIT License
Classifier: Programming Language :: Python
Classifier: Programming Language :: Python :: 2.7
Classifier: Programming Language :: Python :: 3.0
Classifier: Programming Language :: Python :: 3.1
Classifier: Programming Language :: Python :: 3.2
Classifier: Programming Language :: Python :: 3.3
Classifier: Programming Language :: Python :: 3.4
Classifier: Programming Language :: Python :: 3.5
Classifier: Programming Language :: Python :: 3.6
Classifier: Programming Language :: Python :: Implementation :: PyPy
Requires-Dist: numpy (>=1.14.2)
Requires-Dist: pprintpp (>=0.3.0)
Requires-Dist: pytest (>=3.5.0)
Requires-Dist: pytest-cov (>=2.5.1)
Requires-Dist: wheel (>=0.30.0)
